{
  "errors": [
    {
      "message": "Forbidden access",
      "extensions": {
        "error": {
          "name": "ForbiddenError",
          "message": "Forbidden access",
          "details": {}
        },
        "code": "FORBIDDEN"
      }
    }
  ],
  "data": {
    "grandPrixes": {
      "data": [
        {
          "id": "40",
          "attributes": {
            "name": "Malaysia GP 25",
            "startDate": "2025-10-24T02:45:00.000Z",
            "fullName": "GRAND PRIX OF MALAYSIA",
            "endDate": "2025-10-26T07:45:00.000Z",
            "round": "20",
            "season": null,
            "track": {
              "data": {
                "id": "19",
                "attributes": {
                  "name": "Petronas Sepang International Circuit",
                  "imageOutline": "https://purple-sector-bucket.s3.ap-south-1.amazonaws.com/tracks/sepang_malaysia.png",
                  "image": "https://purple-sector-bucket.s3.ap-south-1.amazonaws.com/tracks/sepang_malaysia.png",
                  "imageFancy": null,
                  "city": null,
                  "country": "Malaysia",
                  "latitude": 2.76126719034395,
                  "longitude": 101.73774624664388
                }
              }
            }
          }
        }
      ]
    },
    "races": {
      "data": []
    }
  }
}